<Annotation>
	<CharAnno><Char id="239" label="&#6035;" lineid="0">
		<coor xmin="424" ymin="33" />
		<coor xmax="502" ymax="110" />
	</Char></CharAnno>
	<CharAnno><Char id="263" label="&#6042;" lineid="1">
		<coor xmin="290" ymin="114" />
		<coor xmax="324" ymax="164" />
	</Char></CharAnno>
	<CharAnno><Char id="269" label="&#6047;" lineid="1">
		<coor xmin="520" ymin="107" />
		<coor xmax="602" ymax="170" />
	</Char></CharAnno>
	<CharAnno><Char id="283" label="&#6047;" lineid="2">
		<coor xmin="302" ymin="185" />
		<coor xmax="382" ymax="240" />
	</Char></CharAnno>
	<CharAnno><Char id="285" label="&#6035;" lineid="2">
		<coor xmin="612" ymin="183" />
		<coor xmax="685" ymax="244" />
	</Char></CharAnno>
	<CharAnno><Char id="294" label="&#6042;" lineid="3">
		<coor xmin="310" ymin="265" />
		<coor xmax="348" ymax="318" />
	</Char></CharAnno>
	<CharAnno><Char id="295" label="&#6040;" lineid="3">
		<coor xmin="346" ymin="259" />
		<coor xmax="414" ymax="318" />
	</Char></CharAnno>
	<CharAnno><Char id="296" label="&#6016;" lineid="3">
		<coor xmin="420" ymin="256" />
		<coor xmax="490" ymax="316" />
	</Char></CharAnno>
	<CharAnno><Char id="301" label="&#6042;" lineid="3">
		<coor xmin="641" ymin="267" />
		<coor xmax="688" ymax="314" />
	</Char></CharAnno>
	<CharAnno><Char id="317" label="&#6035;" lineid="4">
		<coor xmin="81" ymin="335" />
		<coor xmax="166" ymax="398" />
	</Char></CharAnno>
	<CharAnno><Char id="321" label="&#6016;" lineid="4">
		<coor xmin="304" ymin="335" />
		<coor xmax="366" ymax="391" />
	</Char></CharAnno>
	<CharAnno><Char id="326" label="&#6042;" lineid="4">
		<coor xmin="568" ymin="345" />
		<coor xmax="598" ymax="391" />
	</Char></CharAnno>
	<CharAnno><Char id="327" label="&#6047;" lineid="4">
		<coor xmin="605" ymin="341" />
		<coor xmax="682" ymax="389" />
	</Char></CharAnno>
	<CharAnno><Char id="339" label="&#6035;" lineid="4">
		<coor xmin="908" ymin="339" />
		<coor xmax="992" ymax="399" />
	</Char></CharAnno>
	<CharAnno><Char id="340" label="&#6035;" lineid="1">
		<coor xmin="764" ymin="109" />
		<coor xmax="846" ymax="175" />
	</Char></CharAnno>
	<CharAnno><Char id="345" label="&#6016;" lineid="0">
		<coor xmin="1068" ymin="23" />
		<coor xmax="1136" ymax="95" />
	</Char></CharAnno>
	<CharAnno><Char id="346" label="&#6040;" lineid="0">
		<coor xmin="1144" ymin="37" />
		<coor xmax="1219" ymax="90" />
	</Char></CharAnno>
	<CharAnno><Char id="351" label="&#6016;" lineid="1">
		<coor xmin="1066" ymin="110" />
		<coor xmax="1131" ymax="165" />
	</Char></CharAnno>
	<CharAnno><Char id="354" label="&#6035;" lineid="1">
		<coor xmin="1220" ymin="109" />
		<coor xmax="1288" ymax="175" />
	</Char></CharAnno>
	<CharAnno><Char id="358" label="&#6040;" lineid="2">
		<coor xmin="877" ymin="190" />
		<coor xmax="943" ymax="238" />
	</Char></CharAnno>
	<CharAnno><Char id="359" label="&#6016;" lineid="2">
		<coor xmin="951" ymin="176" />
		<coor xmax="1032" ymax="244" />
	</Char></CharAnno>
	<CharAnno><Char id="362" label="&#6047;" lineid="2">
		<coor xmin="1106" ymin="182" />
		<coor xmax="1185" ymax="240" />
	</Char></CharAnno>
</Annotation>