<Annotation>
	<CharAnno><Char id="13" label="&#6035;" lineid="0">
		<coor xmin="1544" ymin="78" />
		<coor xmax="1607" ymax="154" />
	</Char></CharAnno>
	<CharAnno><Char id="15" label="&#6042;" lineid="0">
		<coor xmin="1680" ymin="75" />
		<coor xmax="1716" ymax="156" />
	</Char></CharAnno>
	<CharAnno><Char id="53" label="&#6035;" lineid="1">
		<coor xmin="721" ymin="179" />
		<coor xmax="791" ymax="257" />
	</Char></CharAnno>
	<CharAnno><Char id="57" label="&#6035;" lineid="1">
		<coor xmin="882" ymin="173" />
		<coor xmax="963" ymax="263" />
	</Char></CharAnno>
	<CharAnno><Char id="59" label="&#6040;" lineid="2">
		<coor xmin="605" ymin="296" />
		<coor xmax="687" ymax="375" />
	</Char></CharAnno>
	<CharAnno><Char id="62" label="&#6016;" lineid="2">
		<coor xmin="736" ymin="305" />
		<coor xmax="785" ymax="372" />
	</Char></CharAnno>
	<CharAnno><Char id="65" label="&#6042;" lineid="2">
		<coor xmin="920" ymin="284" />
		<coor xmax="969" ymax="372" />
	</Char></CharAnno>
	<CharAnno><Char id="72" label="&#6035;" lineid="1">
		<coor xmin="1197" ymin="181" />
		<coor xmax="1249" ymax="260" />
	</Char></CharAnno>
	<CharAnno><Char id="75" label="&#6047;" lineid="1">
		<coor xmin="1291" ymin="184" />
		<coor xmax="1366" ymax="253" />
	</Char></CharAnno>
	<CharAnno><Char id="77" label="&#6016;" lineid="1">
		<coor xmin="1366" ymin="173" />
		<coor xmax="1438" ymax="276" />
	</Char></CharAnno>
	<CharAnno><Char id="78" label="&#6016;" lineid="1">
		<coor xmin="1435" ymin="180" />
		<coor xmax="1506" ymax="255" />
	</Char></CharAnno>
	<CharAnno><Char id="81" label="&#6047;" lineid="1">
		<coor xmin="1505" ymin="188" />
		<coor xmax="1572" ymax="258" />
	</Char></CharAnno>
	<CharAnno><Char id="82" label="&#6035;" lineid="1">
		<coor xmin="1572" ymin="185" />
		<coor xmax="1619" ymax="256" />
	</Char></CharAnno>
	<CharAnno><Char id="84" label="&#6042;" lineid="1">
		<coor xmin="1645" ymin="178" />
		<coor xmax="1683" ymax="258" />
	</Char></CharAnno>
	<CharAnno><Char id="183" label="&#6016;" lineid="1">
		<coor xmin="2310" ymin="178" />
		<coor xmax="2369" ymax="255" />
	</Char></CharAnno>
	<CharAnno><Char id="266" label="&#6016;" lineid="2">
		<coor xmin="1850" ymin="296" />
		<coor xmax="1913" ymax="383" />
	</Char></CharAnno>
	<CharAnno><Char id="346" label="&#6047;" lineid="3">
		<coor xmin="1037" ymin="412" />
		<coor xmax="1105" ymax="485" />
	</Char></CharAnno>
	<CharAnno><Char id="350" label="&#6016;" lineid="3">
		<coor xmin="1258" ymin="418" />
		<coor xmax="1316" ymax="489" />
	</Char></CharAnno>
	<CharAnno><Char id="357" label="&#6040;" lineid="3">
		<coor xmin="1665" ymin="417" />
		<coor xmax="1729" ymax="486" />
	</Char></CharAnno>
	<CharAnno><Char id="364" label="&#6016;" lineid="3">
		<coor xmin="2130" ymin="428" />
		<coor xmax="2193" ymax="496" />
	</Char></CharAnno>
	<CharAnno><Char id="456" label="&#6016;" lineid="4">
		<coor xmin="652" ymin="530" />
		<coor xmax="723" ymax="622" />
	</Char></CharAnno>
	<CharAnno><Char id="457" label="&#6047;" lineid="4">
		<coor xmin="714" ymin="539" />
		<coor xmax="794" ymax="631" />
	</Char></CharAnno>
	<CharAnno><Char id="474" label="&#6047;" lineid="4">
		<coor xmin="1799" ymin="541" />
		<coor xmax="1872" ymax="647" />
	</Char></CharAnno>
	<CharAnno><Char id="476" label="&#6040;" lineid="4">
		<coor xmin="1907" ymin="553" />
		<coor xmax="1961" ymax="622" />
	</Char></CharAnno>
	<CharAnno><Char id="582" label="&#6016;" lineid="0">
		<coor xmin="794" ymin="67" />
		<coor xmax="851" ymax="139" />
	</Char></CharAnno>
	<CharAnno><Char id="587" label="&#6042;" lineid="3">
		<coor xmin="954" ymin="420" />
		<coor xmax="993" ymax="487" />
	</Char></CharAnno>
	<CharAnno><Char id="589" label="&#6035;" lineid="2">
		<coor xmin="1230" ymin="301" />
		<coor xmax="1283" ymax="378" />
	</Char></CharAnno>
	<CharAnno><Char id="596" label="&#6047;" lineid="3">
		<coor xmin="1178" ymin="414" />
		<coor xmax="1249" ymax="491" />
	</Char></CharAnno>
	<CharAnno><Char id="597" label="&#6042;" lineid="3">
		<coor xmin="1321" ymin="416" />
		<coor xmax="1353" ymax="489" />
	</Char></CharAnno>
	<CharAnno><Char id="609" label="&#6035;" lineid="4">
		<coor xmin="1661" ymin="554" />
		<coor xmax="1720" ymax="626" />
	</Char></CharAnno>
	<CharAnno><Char id="612" label="&#6035;" lineid="3">
		<coor xmin="1907" ymin="418" />
		<coor xmax="1957" ymax="492" />
	</Char></CharAnno>
</Annotation>