<Annotation>
	<CharAnno><Char id="7" label="&#6047;" lineid="0">
		<coor xmin="988" ymin="103" />
		<coor xmax="1080" ymax="181" />
	</Char></CharAnno>
	<CharAnno><Char id="30" label="&#6042;" lineid="2">
		<coor xmin="1149" ymin="330" />
		<coor xmax="1190" ymax="396" />
	</Char></CharAnno>
	<CharAnno><Char id="36" label="&#6040;" lineid="0">
		<coor xmin="1391" ymin="103" />
		<coor xmax="1459" ymax="176" />
	</Char></CharAnno>
	<CharAnno><Char id="39" label="&#6042;" lineid="0">
		<coor xmin="1587" ymin="101" />
		<coor xmax="1629" ymax="173" />
	</Char></CharAnno>
	<CharAnno><Char id="42" label="&#6035;" lineid="1">
		<coor xmin="1645" ymin="215" />
		<coor xmax="1710" ymax="290" />
	</Char></CharAnno>
	<CharAnno><Char id="44" label="&#6040;" lineid="1">
		<coor xmin="1565" ymin="221" />
		<coor xmax="1627" ymax="291" />
	</Char></CharAnno>
	<CharAnno><Char id="46" label="&#6035;" lineid="1">
		<coor xmin="1461" ymin="215" />
		<coor xmax="1529" ymax="291" />
	</Char></CharAnno>
	<CharAnno><Char id="58" label="&#6040;" lineid="3">
		<coor xmin="1293" ymin="444" />
		<coor xmax="1351" ymax="514" />
	</Char></CharAnno>
	<CharAnno><Char id="61" label="&#6035;" lineid="3">
		<coor xmin="1129" ymin="441" />
		<coor xmax="1197" ymax="514" />
	</Char></CharAnno>
	<CharAnno><Char id="64" label="&#6042;" lineid="3">
		<coor xmin="1014" ymin="437" />
		<coor xmax="1053" ymax="511" />
	</Char></CharAnno>
	<CharAnno><Char id="66" label="&#6016;" lineid="3">
		<coor xmin="852" ymin="429" />
		<coor xmax="932" ymax="507" />
	</Char></CharAnno>
	<CharAnno><Char id="77" label="&#6040;" lineid="4">
		<coor xmin="1117" ymin="564" />
		<coor xmax="1189" ymax="638" />
	</Char></CharAnno>
	<CharAnno><Char id="87" label="&#6047;" lineid="2">
		<coor xmin="1694" ymin="324" />
		<coor xmax="1779" ymax="405" />
	</Char></CharAnno>
	<CharAnno><Char id="94" label="&#6016;" lineid="4">
		<coor xmin="1777" ymin="560" />
		<coor xmax="1839" ymax="631" />
	</Char></CharAnno>
	<CharAnno><Char id="97" label="&#6016;" lineid="4">
		<coor xmin="1864" ymin="563" />
		<coor xmax="1929" ymax="635" />
	</Char></CharAnno>
	<CharAnno><Char id="98" label="&#6040;" lineid="4">
		<coor xmin="1941" ymin="564" />
		<coor xmax="2020" ymax="639" />
	</Char></CharAnno>
	<CharAnno><Char id="99" label="&#6042;" lineid="4">
		<coor xmin="2005" ymin="561" />
		<coor xmax="2050" ymax="636" />
	</Char></CharAnno>
	<CharAnno><Char id="102" label="&#6047;" lineid="3">
		<coor xmin="2048" ymin="433" />
		<coor xmax="2125" ymax="506" />
	</Char></CharAnno>
	<CharAnno><Char id="116" label="&#6035;" lineid="1">
		<coor xmin="2046" ymin="206" />
		<coor xmax="2115" ymax="285" />
	</Char></CharAnno>
	<CharAnno><Char id="118" label="&#6016;" lineid="0">
		<coor xmin="2086" ymin="98" />
		<coor xmax="2149" ymax="170" />
	</Char></CharAnno>
	<CharAnno><Char id="119" label="&#6040;" lineid="0">
		<coor xmin="2156" ymin="95" />
		<coor xmax="2219" ymax="167" />
	</Char></CharAnno>
	<CharAnno><Char id="121" label="&#6035;" lineid="0">
		<coor xmin="2244" ymin="101" />
		<coor xmax="2316" ymax="168" />
	</Char></CharAnno>
	<CharAnno><Char id="124" label="&#6035;" lineid="1">
		<coor xmin="2238" ymin="213" />
		<coor xmax="2302" ymax="289" />
	</Char></CharAnno>
	<CharAnno><Char id="129" label="&#6042;" lineid="0">
		<coor xmin="2423" ymin="97" />
		<coor xmax="2466" ymax="170" />
	</Char></CharAnno>
	<CharAnno><Char id="138" label="&#6016;" lineid="2">
		<coor xmin="2076" ymin="322" />
		<coor xmax="2130" ymax="395" />
	</Char></CharAnno>
	<CharAnno><Char id="139" label="&#6042;" lineid="0">
		<coor xmin="2641" ymin="101" />
		<coor xmax="2690" ymax="176" />
	</Char></CharAnno>
	<CharAnno><Char id="205" label="&#6042;" lineid="4">
		<coor xmin="2137" ymin="568" />
		<coor xmax="2182" ymax="642" />
	</Char></CharAnno>
	<CharAnno><Char id="206" label="&#6016;" lineid="4">
		<coor xmin="2070" ymin="568" />
		<coor xmax="2132" ymax="644" />
	</Char></CharAnno>
	<CharAnno><Char id="209" label="&#6040;" lineid="3">
		<coor xmin="2195" ymin="433" />
		<coor xmax="2259" ymax="508" />
	</Char></CharAnno>
	<CharAnno><Char id="211" label="&#6035;" lineid="3">
		<coor xmin="2294" ymin="437" />
		<coor xmax="2366" ymax="518" />
	</Char></CharAnno>
	<CharAnno><Char id="214" label="&#6016;" lineid="4">
		<coor xmin="2244" ymin="571" />
		<coor xmax="2305" ymax="640" />
	</Char></CharAnno>
	<CharAnno><Char id="217" label="&#6016;" lineid="4">
		<coor xmin="2500" ymin="560" />
		<coor xmax="2567" ymax="631" />
	</Char></CharAnno>
</Annotation>