<Annotation>
	<CharAnno><Char id="42" label="&#6040;" lineid="0">
		<coor xmin="34" ymin="108" />
		<coor xmax="75" ymax="149" />
	</Char></CharAnno>
	<CharAnno><Char id="44" label="&#6035;" lineid="0">
		<coor xmin="98" ymin="104" />
		<coor xmax="146" ymax="155" />
	</Char></CharAnno>
	<CharAnno><Char id="62" label="&#6047;" lineid="0">
		<coor xmin="542" ymin="100" />
		<coor xmax="596" ymax="146" />
	</Char></CharAnno>
	<CharAnno><Char id="68" label="&#6042;" lineid="0">
		<coor xmin="758" ymin="101" />
		<coor xmax="787" ymax="144" />
	</Char></CharAnno>
	<CharAnno><Char id="69" label="&#6016;" lineid="0">
		<coor xmin="788" ymin="101" />
		<coor xmax="838" ymax="152" />
	</Char></CharAnno>
	<CharAnno><Char id="72" label="&#6016;" lineid="0">
		<coor xmin="886" ymin="97" />
		<coor xmax="936" ymax="147" />
	</Char></CharAnno>
	<CharAnno><Char id="75" label="&#6047;" lineid="0">
		<coor xmin="952" ymin="99" />
		<coor xmax="1005" ymax="138" />
	</Char></CharAnno>
	<CharAnno><Char id="92" label="&#6047;" lineid="0">
		<coor xmin="1559" ymin="84" />
		<coor xmax="1603" ymax="137" />
	</Char></CharAnno>
	<CharAnno><Char id="96" label="&#6042;" lineid="0">
		<coor xmin="1784" ymin="85" />
		<coor xmax="1813" ymax="131" />
	</Char></CharAnno>
	<CharAnno><Char id="173" label="&#6042;" lineid="1">
		<coor xmin="202" ymin="199" />
		<coor xmax="234" ymax="247" />
	</Char></CharAnno>
	<CharAnno><Char id="176" label="&#6042;" lineid="1">
		<coor xmin="255" ymin="196" />
		<coor xmax="278" ymax="239" />
	</Char></CharAnno>
	<CharAnno><Char id="177" label="&#6016;" lineid="1">
		<coor xmin="280" ymin="195" />
		<coor xmax="333" ymax="251" />
	</Char></CharAnno>
	<CharAnno><Char id="178" label="&#6042;" lineid="1">
		<coor xmin="327" ymin="195" />
		<coor xmax="354" ymax="245" />
	</Char></CharAnno>
	<CharAnno><Char id="183" label="&#6042;" lineid="1">
		<coor xmin="513" ymin="198" />
		<coor xmax="539" ymax="245" />
	</Char></CharAnno>
	<CharAnno><Char id="184" label="&#6016;" lineid="1">
		<coor xmin="543" ymin="188" />
		<coor xmax="592" ymax="257" />
	</Char></CharAnno>
	<CharAnno><Char id="186" label="&#6042;" lineid="1">
		<coor xmin="640" ymin="194" />
		<coor xmax="671" ymax="241" />
	</Char></CharAnno>
	<CharAnno><Char id="190" label="&#6042;" lineid="1">
		<coor xmin="770" ymin="189" />
		<coor xmax="800" ymax="241" />
	</Char></CharAnno>
	<CharAnno><Char id="192" label="&#6035;" lineid="1">
		<coor xmin="829" ymin="200" />
		<coor xmax="877" ymax="243" />
	</Char></CharAnno>
	<CharAnno><Char id="199" label="&#6016;" lineid="1">
		<coor xmin="1145" ymin="191" />
		<coor xmax="1201" ymax="243" />
	</Char></CharAnno>
	<CharAnno><Char id="203" label="&#6047;" lineid="1">
		<coor xmin="1229" ymin="190" />
		<coor xmax="1287" ymax="228" />
	</Char></CharAnno>
	<CharAnno><Char id="206" label="&#6040;" lineid="1">
		<coor xmin="1317" ymin="186" />
		<coor xmax="1366" ymax="233" />
	</Char></CharAnno>
	<CharAnno><Char id="207" label="&#6047;" lineid="1">
		<coor xmin="1364" ymin="183" />
		<coor xmax="1422" ymax="235" />
	</Char></CharAnno>
	<CharAnno><Char id="213" label="&#6016;" lineid="1">
		<coor xmin="1489" ymin="186" />
		<coor xmax="1543" ymax="252" />
	</Char></CharAnno>
	<CharAnno><Char id="215" label="&#6035;" lineid="1">
		<coor xmin="1572" ymin="197" />
		<coor xmax="1630" ymax="240" />
	</Char></CharAnno>
	<CharAnno><Char id="372" label="&#6047;" lineid="4">
		<coor xmin="71" ymin="471" />
		<coor xmax="130" ymax="515" />
	</Char></CharAnno>
	<CharAnno><Char id="374" label="&#6042;" lineid="4">
		<coor xmin="132" ymin="474" />
		<coor xmax="156" ymax="517" />
	</Char></CharAnno>
	<CharAnno><Char id="383" label="&#6047;" lineid="4">
		<coor xmin="290" ymin="468" />
		<coor xmax="350" ymax="512" />
	</Char></CharAnno>
	<CharAnno><Char id="390" label="&#6035;" lineid="3">
		<coor xmin="277" ymin="373" />
		<coor xmax="327" ymax="422" />
	</Char></CharAnno>
	<CharAnno><Char id="392" label="&#6035;" lineid="2">
		<coor xmin="350" ymin="284" />
		<coor xmax="387" ymax="326" />
	</Char></CharAnno>
	<CharAnno><Char id="396" label="&#6035;" lineid="3">
		<coor xmin="377" ymin="379" />
		<coor xmax="416" ymax="424" />
	</Char></CharAnno>
	<CharAnno><Char id="403" label="&#6016;" lineid="2">
		<coor xmin="458" ymin="281" />
		<coor xmax="506" ymax="336" />
	</Char></CharAnno>
	<CharAnno><Char id="408" label="&#6047;" lineid="3">
		<coor xmin="436" ymin="369" />
		<coor xmax="492" ymax="417" />
	</Char></CharAnno>
	<CharAnno><Char id="419" label="&#6016;" lineid="4">
		<coor xmin="669" ymin="472" />
		<coor xmax="719" ymax="523" />
	</Char></CharAnno>
	<CharAnno><Char id="422" label="&#6042;" lineid="2">
		<coor xmin="618" ymin="279" />
		<coor xmax="644" ymax="320" />
	</Char></CharAnno>
	<CharAnno><Char id="426" label="&#6016;" lineid="2">
		<coor xmin="720" ymin="279" />
		<coor xmax="766" ymax="325" />
	</Char></CharAnno>
	<CharAnno><Char id="430" label="&#6035;" lineid="3">
		<coor xmin="646" ymin="380" />
		<coor xmax="696" ymax="419" />
	</Char></CharAnno>
	<CharAnno><Char id="434" label="&#6035;" lineid="3">
		<coor xmin="759" ymin="373" />
		<coor xmax="809" ymax="420" />
	</Char></CharAnno>
	<CharAnno><Char id="439" label="&#6016;" lineid="4">
		<coor xmin="797" ymin="465" />
		<coor xmax="855" ymax="518" />
	</Char></CharAnno>
	<CharAnno><Char id="440" label="&#6047;" lineid="3">
		<coor xmin="862" ymin="379" />
		<coor xmax="923" ymax="424" />
	</Char></CharAnno>
	<CharAnno><Char id="448" label="&#6035;" lineid="3">
		<coor xmin="1095" ymin="379" />
		<coor xmax="1138" ymax="422" />
	</Char></CharAnno>
	<CharAnno><Char id="453" label="&#6016;" lineid="2">
		<coor xmin="1051" ymin="275" />
		<coor xmax="1093" ymax="327" />
	</Char></CharAnno>
	<CharAnno><Char id="459" label="&#6035;" lineid="2">
		<coor xmin="1236" ymin="276" />
		<coor xmax="1276" ymax="325" />
	</Char></CharAnno>
	<CharAnno><Char id="479" label="&#6040;" lineid="2">
		<coor xmin="1317" ymin="280" />
		<coor xmax="1364" ymax="322" />
	</Char></CharAnno>
	<CharAnno><Char id="486" label="&#6016;" lineid="3">
		<coor xmin="1326" ymin="376" />
		<coor xmax="1367" ymax="423" />
	</Char></CharAnno>
	<CharAnno><Char id="491" label="&#6047;" lineid="3">
		<coor xmin="1390" ymin="370" />
		<coor xmax="1439" ymax="418" />
	</Char></CharAnno>
	<CharAnno><Char id="498" label="&#6016;" lineid="4">
		<coor xmin="1401" ymin="462" />
		<coor xmax="1451" ymax="510" />
	</Char></CharAnno>
	<CharAnno><Char id="500" label="&#6042;" lineid="4">
		<coor xmin="1454" ymin="466" />
		<coor xmax="1476" ymax="503" />
	</Char></CharAnno>
	<CharAnno><Char id="509" label="&#6042;" lineid="2">
		<coor xmin="1581" ymin="273" />
		<coor xmax="1617" ymax="317" />
	</Char></CharAnno>
	<CharAnno><Char id="512" label="&#6016;" lineid="2">
		<coor xmin="1672" ymin="271" />
		<coor xmax="1728" ymax="324" />
	</Char></CharAnno>
	<CharAnno><Char id="640" label="&#6016;" lineid="3">
		<coor xmin="1219" ymin="379" />
		<coor xmax="1261" ymax="417" />
	</Char></CharAnno>
</Annotation>