<Annotation>
	<CharAnno><Char id="328" label="&#6016;" lineid="4">
		<coor xmin="337" ymin="375" />
		<coor xmax="402" ymax="425" />
	</Char></CharAnno>
	<CharAnno><Char id="330" label="&#6035;" lineid="1">
		<coor xmin="328" ymin="132" />
		<coor xmax="388" ymax="177" />
	</Char></CharAnno>
	<CharAnno><Char id="332" label="&#6035;" lineid="1">
		<coor xmin="389" ymin="128" />
		<coor xmax="457" ymax="195" />
	</Char></CharAnno>
	<CharAnno><Char id="336" label="&#6035;" lineid="1">
		<coor xmin="451" ymin="131" />
		<coor xmax="499" ymax="186" />
	</Char></CharAnno>
	<CharAnno><Char id="341" label="&#6042;" lineid="2">
		<coor xmin="483" ymin="216" />
		<coor xmax="510" ymax="263" />
	</Char></CharAnno>
	<CharAnno><Char id="361" label="&#6042;" lineid="3">
		<coor xmin="619" ymin="289" />
		<coor xmax="660" ymax="342" />
	</Char></CharAnno>
	<CharAnno><Char id="362" label="&#6047;" lineid="4">
		<coor xmin="561" ymin="369" />
		<coor xmax="620" ymax="418" />
	</Char></CharAnno>
	<CharAnno><Char id="365" label="&#6042;" lineid="1">
		<coor xmin="577" ymin="122" />
		<coor xmax="618" ymax="185" />
	</Char></CharAnno>
	<CharAnno><Char id="371" label="&#6016;" lineid="0">
		<coor xmin="675" ymin="52" />
		<coor xmax="740" ymax="106" />
	</Char></CharAnno>
	<CharAnno><Char id="373" label="&#6035;" lineid="2">
		<coor xmin="663" ymin="213" />
		<coor xmax="710" ymax="263" />
	</Char></CharAnno>
	<CharAnno><Char id="376" label="&#6035;" lineid="2">
		<coor xmin="752" ymin="210" />
		<coor xmax="801" ymax="262" />
	</Char></CharAnno>
	<CharAnno><Char id="379" label="&#6042;" lineid="3">
		<coor xmin="759" ymin="291" />
		<coor xmax="796" ymax="338" />
	</Char></CharAnno>
	<CharAnno><Char id="383" label="&#6040;" lineid="3">
		<coor xmin="900" ymin="290" />
		<coor xmax="956" ymax="338" />
	</Char></CharAnno>
	<CharAnno><Char id="389" label="&#6035;" lineid="4">
		<coor xmin="783" ymin="366" />
		<coor xmax="851" ymax="433" />
	</Char></CharAnno>
	<CharAnno><Char id="391" label="&#6016;" lineid="1">
		<coor xmin="764" ymin="130" />
		<coor xmax="824" ymax="195" />
	</Char></CharAnno>
	<CharAnno><Char id="395" label="&#6016;" lineid="1">
		<coor xmin="874" ymin="131" />
		<coor xmax="937" ymax="191" />
	</Char></CharAnno>
	<CharAnno><Char id="400" label="&#6042;" lineid="4">
		<coor xmin="1001" ymin="361" />
		<coor xmax="1033" ymax="421" />
	</Char></CharAnno>
	<CharAnno><Char id="404" label="&#6035;" lineid="4">
		<coor xmin="1222" ymin="365" />
		<coor xmax="1293" ymax="426" />
	</Char></CharAnno>
	<CharAnno><Char id="407" label="&#6042;" lineid="3">
		<coor xmin="1082" ymin="285" />
		<coor xmax="1120" ymax="343" />
	</Char></CharAnno>
	<CharAnno><Char id="416" label="&#6042;" lineid="0">
		<coor xmin="1268" ymin="51" />
		<coor xmax="1298" ymax="98" />
	</Char></CharAnno>
	<CharAnno><Char id="420" label="&#6035;" lineid="0">
		<coor xmin="1137" ymin="45" />
		<coor xmax="1200" ymax="108" />
	</Char></CharAnno>
	<CharAnno><Char id="421" label="&#6040;" lineid="0">
		<coor xmin="1066" ymin="51" />
		<coor xmax="1117" ymax="105" />
	</Char></CharAnno>
	<CharAnno><Char id="440" label="&#6042;" lineid="2">
		<coor xmin="1017" ymin="216" />
		<coor xmax="1054" ymax="259" />
	</Char></CharAnno>
</Annotation>