<Annotation>
	<SubSylAnno><SubSyl id="0" label="&#6016;&#6070;">
		<coor xmin="669" ymin="72" />
		<coor xmax="764" ymax="126" />
	</SubSyl></SubSylAnno>
	<SubSylAnno><SubSyl id="1" label="&#6043;">
		<coor xmin="762" ymin="68" />
		<coor xmax="843" ymax="122" />
	</SubSyl></SubSylAnno>
	<SubSylAnno><SubSyl id="4" label="&#6026;&#6076;">
		<coor xmin="1053" ymin="48" />
		<coor xmax="1116" ymax="130" />
	</SubSyl></SubSylAnno>
	<SubSylAnno><SubSyl id="5" label="&#6021;">
		<coor xmin="1108" ymin="64" />
		<coor xmax="1176" ymax="114" />
	</SubSyl></SubSylAnno>
	<SubSylAnno><SubSyl id="6" label="&#6034;">
		<coor xmin="1177" ymin="63" />
		<coor xmax="1241" ymax="117" />
	</SubSyl></SubSylAnno>
	<SubSylAnno><SubSyl id="7" label="&#6040;&#6092;">
		<coor xmin="1245" ymin="35" />
		<coor xmax="1325" ymax="111" />
	</SubSyl></SubSylAnno>
	<SubSylAnno><SubSyl id="8" label="&#6026;&#6078;">
		<coor xmin="1317" ymin="39" />
		<coor xmax="1408" ymax="108" />
	</SubSyl></SubSylAnno>
	<SubSylAnno><SubSyl id="9" label="&#6040;">
		<coor xmin="1407" ymin="58" />
		<coor xmax="1477" ymax="103" />
	</SubSyl></SubSylAnno>
	<SubSylAnno><SubSyl id="10" label="&#6033;">
		<coor xmin="1473" ymin="50" />
		<coor xmax="1539" ymax="105" />
	</SubSyl></SubSylAnno>
	<SubSylAnno><SubSyl id="11" label="&#6020;">
		<coor xmin="1535" ymin="53" />
		<coor xmax="1616" ymax="106" />
	</SubSyl></SubSylAnno>
	<SubSylAnno><SubSyl id="12" label="&#6047;&#6076;">
		<coor xmin="602" ymin="151" />
		<coor xmax="673" ymax="218" />
	</SubSyl></SubSylAnno>
	<SubSylAnno><SubSyl id="13" label="&#6030;&#6098;&#6041;">
		<coor xmin="671" ymin="153" />
		<coor xmax="814" ymax="225" />
	</SubSyl></SubSylAnno>
	<SubSylAnno><SubSyl id="14" label="&#6038;&#6080;">
		<coor xmin="603" ymin="209" />
		<coor xmax="735" ymax="307" />
	</SubSyl></SubSylAnno>
	<SubSylAnno><SubSyl id="15" label="&#6042;">
		<coor xmin="745" ymin="234" />
		<coor xmax="781" ymax="280" />
	</SubSyl></SubSylAnno>
	<SubSylAnno><SubSyl id="16" label="&#6016;&#6076;">
		<coor xmin="783" ymin="226" />
		<coor xmax="848" ymax="298" />
	</SubSyl></SubSylAnno>
	<SubSylAnno><SubSyl id="17" label="&#6035;">
		<coor xmin="851" ymin="225" />
		<coor xmax="926" ymax="280" />
	</SubSyl></SubSylAnno>
	<SubSylAnno><SubSyl id="18" label="&#6023;&#6070;">
		<coor xmin="914" ymin="214" />
		<coor xmax="1003" ymax="274" />
	</SubSyl></SubSylAnno>
	<SubSylAnno><SubSyl id="19" label="&#6036;&#6091;">
		<coor xmin="996" ymin="202" />
		<coor xmax="1069" ymax="273" />
	</SubSyl></SubSylAnno>
	<SubSylAnno><SubSyl id="20" label="&#6036;&#6070;&#6098;&#6042;">
		<coor xmin="1066" ymin="186" />
		<coor xmax="1158" ymax="288" />
	</SubSyl></SubSylAnno>
	<SubSylAnno><SubSyl id="21" label="&#6035;">
		<coor xmin="1159" ymin="217" />
		<coor xmax="1236" ymax="278" />
	</SubSyl></SubSylAnno>
	<SubSylAnno><SubSyl id="22" label="&#6035;&#6072;">
		<coor xmin="1007" ymin="128" />
		<coor xmax="1088" ymax="196" />
	</SubSyl></SubSylAnno>
	<SubSylAnno><SubSyl id="24" label="&#6041;&#6070;">
		<coor xmin="1073" ymin="141" />
		<coor xmax="1197" ymax="191" />
	</SubSyl></SubSylAnno>
	<SubSylAnno><SubSyl id="25" label="&#6041;">
		<coor xmin="1197" ymin="146" />
		<coor xmax="1291" ymax="191" />
	</SubSyl></SubSylAnno>
	<SubSylAnno><SubSyl id="26" label="&#6038;&#6072;">
		<coor xmin="1289" ymin="120" />
		<coor xmax="1359" ymax="189" />
	</SubSyl></SubSylAnno>
	<SubSylAnno><SubSyl id="27" label="&#6040;&#6098;&#6026;&#6070;">
		<coor xmin="1346" ymin="142" />
		<coor xmax="1442" ymax="217" />
	</SubSyl></SubSylAnno>
	<SubSylAnno><SubSyl id="28" label="&#6041;">
		<coor xmin="1439" ymin="145" />
		<coor xmax="1538" ymax="191" />
	</SubSyl></SubSylAnno>
	<SubSylAnno><SubSyl id="29" label="&#6035;&#6073;">
		<coor xmin="1527" ymin="120" />
		<coor xmax="1613" ymax="194" />
	</SubSyl></SubSylAnno>
	<SubSylAnno><SubSyl id="30" label="&#6020;">
		<coor xmin="1603" ymin="139" />
		<coor xmax="1676" ymax="192" />
	</SubSyl></SubSylAnno>
	<SubSylAnno><SubSyl id="31" label="&#6031;&#6082;">
		<coor xmin="1376" ymin="203" />
		<coor xmax="1490" ymax="270" />
	</SubSyl></SubSylAnno>
	<SubSylAnno><SubSyl id="32" label="&#6047;&#6098;&#6042;&#6076;">
		<coor xmin="1483" ymin="194" />
		<coor xmax="1571" ymax="297" />
	</SubSyl></SubSylAnno>
	<SubSylAnno><SubSyl id="33" label="&#6044;">
		<coor xmin="1566" ymin="217" />
		<coor xmax="1626" ymax="269" />
	</SubSyl></SubSylAnno>
	<SubSylAnno><SubSyl id="34" label="&#6048;&#6070;">
		<coor xmin="723" ymin="298" />
		<coor xmax="838" ymax="353" />
	</SubSyl></SubSylAnno>
	<SubSylAnno><SubSyl id="35" label="&#6043;">
		<coor xmin="836" ymin="299" />
		<coor xmax="923" ymax="350" />
	</SubSyl></SubSylAnno>
	<SubSylAnno><SubSyl id="36" label="&#6047;&#6098;&#6042;&#6076;">
		<coor xmin="915" ymin="281" />
		<coor xmax="1011" ymax="369" />
	</SubSyl></SubSylAnno>
	<SubSylAnno><SubSyl id="37" label="&#6044;">
		<coor xmin="1001" ymin="298" />
		<coor xmax="1060" ymax="348" />
	</SubSyl></SubSylAnno>
	<SubSylAnno><SubSyl id="38" label="&#6023;&#6071;">
		<coor xmin="1053" ymin="282" />
		<coor xmax="1130" ymax="351" />
	</SubSyl></SubSylAnno>
	<SubSylAnno><SubSyl id="39" label="&#6031;">
		<coor xmin="1125" ymin="294" />
		<coor xmax="1190" ymax="345" />
	</SubSyl></SubSylAnno>
	<SubSylAnno><SubSyl id="40" label="&#6035;&#6073;">
		<coor xmin="1183" ymin="278" />
		<coor xmax="1275" ymax="347" />
	</SubSyl></SubSylAnno>
	<SubSylAnno><SubSyl id="41" label="&#6020;">
		<coor xmin="1261" ymin="290" />
		<coor xmax="1335" ymax="340" />
	</SubSyl></SubSylAnno>
	<SubSylAnno><SubSyl id="42" label="&#6040;&#6070;">
		<coor xmin="1321" ymin="292" />
		<coor xmax="1413" ymax="340" />
	</SubSyl></SubSylAnno>
	<SubSylAnno><SubSyl id="43" label="&#6031;&#6070;">
		<coor xmin="1419" ymin="288" />
		<coor xmax="1525" ymax="342" />
	</SubSyl></SubSylAnno>
	<SubSylAnno><SubSyl id="44" label="&#6042;&#6093;">
		<coor xmin="606" ymin="355" />
		<coor xmax="674" ymax="428" />
	</SubSyl></SubSylAnno>
	<SubSylAnno><SubSyl id="45" label="&#6036;">
		<coor xmin="650" ymin="385" />
		<coor xmax="722" ymax="431" />
	</SubSyl></SubSylAnno>
	<SubSylAnno><SubSyl id="46" label="&#6047;&#6091;">
		<coor xmin="725" ymin="366" />
		<coor xmax="803" ymax="427" />
	</SubSyl></SubSylAnno>
	<SubSylAnno><SubSyl id="47" label="&#6016;&#6076;">
		<coor xmin="804" ymin="374" />
		<coor xmax="869" ymax="443" />
	</SubSyl></SubSylAnno>
	<SubSylAnno><SubSyl id="48" label="&#6035;">
		<coor xmin="872" ymin="372" />
		<coor xmax="947" ymax="431" />
	</SubSyl></SubSylAnno>
	<SubSylAnno><SubSyl id="49" label="&#6035;&#6084;&#6087;">
		<coor xmin="938" ymin="372" />
		<coor xmax="1120" ymax="427" />
	</SubSyl></SubSylAnno>
	<SubSylAnno><SubSyl id="50" label="&#6018;&#6070;">
		<coor xmin="1348" ymin="367" />
		<coor xmax="1447" ymax="421" />
	</SubSyl></SubSylAnno>
	<SubSylAnno><SubSyl id="51" label="&#6031;&#6091;">
		<coor xmin="1452" ymin="345" />
		<coor xmax="1520" ymax="418" />
	</SubSyl></SubSylAnno>
	<SubSylAnno><SubSyl id="52" label="&#6044;&#6072;">
		<coor xmin="1518" ymin="349" />
		<coor xmax="1583" ymax="421" />
	</SubSyl></SubSylAnno>
	<SubSylAnno><SubSyl id="54" label="&#6035;">
		<coor xmin="1740" ymin="361" />
		<coor xmax="1816" ymax="418" />
	</SubSyl></SubSylAnno>
	<SubSylAnno><SubSyl id="55" label="&#6036;&#6070;">
		<coor xmin="1646" ymin="362" />
		<coor xmax="1737" ymax="422" />
	</SubSyl></SubSylAnno>
	<SubSylAnno><SubSyl id="56" label="&#6023;">
		<coor xmin="1808" ymin="334" />
		<coor xmax="1887" ymax="412" />
	</SubSyl></SubSylAnno>
	<SubSylAnno><SubSyl id="60" label="&#6065;&#6098;&#6041;">
		<coor xmin="1723" ymin="50" />
		<coor xmax="1809" ymax="132" />
	</SubSyl></SubSylAnno>
	<SubSylAnno><SubSyl id="61" label="&#6040;&#6098;&#6026;&#6070;">
		<coor xmin="1811" ymin="53" />
		<coor xmax="1901" ymax="129" />
	</SubSyl></SubSylAnno>
	<SubSylAnno><SubSyl id="208" label="&#6038;&#6075;&#6086;">
		<coor xmin="1621" ymin="270" />
		<coor xmax="1689" ymax="364" />
	</SubSyl></SubSylAnno>
	<SubSylAnno><SubSyl id="209" label="&#6038;&#6075;&#6086;">
		<coor xmin="1579" ymin="343" />
		<coor xmax="1643" ymax="454" />
	</SubSyl></SubSylAnno>
	<SubSylAnno><SubSyl id="212" label="&#6030;&#6084;&#6087;">
		<coor xmin="843" ymin="64" />
		<coor xmax="1047" ymax="117" />
	</SubSyl></SubSylAnno>
</Annotation>