<Annotation>
	<CharAnno><Char id="136" label="&#6041;" lineid="0">
		<coor xmin="50" ymin="63" />
		<coor xmax="138" ymax="114" />
	</Char></CharAnno>
	<CharAnno><Char id="137" label="&#6043;" lineid="0">
		<coor xmin="135" ymin="66" />
		<coor xmax="222" ymax="116" />
	</Char></CharAnno>
	<CharAnno><Char id="139" label="&#6018;" lineid="0">
		<coor xmin="226" ymin="60" />
		<coor xmax="290" ymax="112" />
	</Char></CharAnno>
	<CharAnno><Char id="142" label="&#6050;" lineid="0">
		<coor xmin="323" ymin="70" />
		<coor xmax="395" ymax="116" />
	</Char></CharAnno>
	<CharAnno><Char id="143" label="&#6047;" lineid="0">
		<coor xmin="399" ymin="67" />
		<coor xmax="482" ymax="122" />
	</Char></CharAnno>
	<CharAnno><Char id="145" label="&#6033;" lineid="0">
		<coor xmin="485" ymin="68" />
		<coor xmax="544" ymax="114" />
	</Char></CharAnno>
	<CharAnno><Char id="148" label="&#6020;" lineid="0">
		<coor xmin="561" ymin="63" />
		<coor xmax="626" ymax="118" />
	</Char></CharAnno>
	<CharAnno><Char id="149" label="&#6040;" lineid="0">
		<coor xmin="625" ymin="62" />
		<coor xmax="699" ymax="114" />
	</Char></CharAnno>
	<CharAnno><Char id="150" label="&#6030;" lineid="0">
		<coor xmin="694" ymin="63" />
		<coor xmax="810" ymax="116" />
	</Char></CharAnno>
	<CharAnno><Char id="152" label="&#6043;" lineid="0">
		<coor xmin="803" ymin="68" />
		<coor xmax="902" ymax="122" />
	</Char></CharAnno>
	<CharAnno><Char id="154" label="&#6050;" lineid="1">
		<coor xmin="170" ymin="136" />
		<coor xmax="243" ymax="187" />
	</Char></CharAnno>
	<CharAnno><Char id="156" label="&#6033;" lineid="1">
		<coor xmin="269" ymin="138" />
		<coor xmax="325" ymax="187" />
	</Char></CharAnno>
	<CharAnno><Char id="158" label="&#6031;" lineid="1">
		<coor xmin="327" ymin="139" />
		<coor xmax="392" ymax="185" />
	</Char></CharAnno>
	<CharAnno><Char id="161" label="&#6018;" lineid="1">
		<coor xmin="431" ymin="134" />
		<coor xmax="497" ymax="188" />
	</Char></CharAnno>
	<CharAnno><Char id="162" label="&#6036;" lineid="1">
		<coor xmin="491" ymin="145" />
		<coor xmax="562" ymax="189" />
	</Char></CharAnno>
	<CharAnno><Char id="163" label="&#6038;" lineid="1">
		<coor xmin="562" ymin="139" />
		<coor xmax="627" ymax="185" />
	</Char></CharAnno>
	<CharAnno><Char id="164" label="&#6035;" lineid="1">
		<coor xmin="627" ymin="139" />
		<coor xmax="685" ymax="191" />
	</Char></CharAnno>
	<CharAnno><Char id="168" label="&#6038;" lineid="1">
		<coor xmin="692" ymin="141" />
		<coor xmax="762" ymax="188" />
	</Char></CharAnno>
	<CharAnno><Char id="170" label="&#6021;" lineid="1">
		<coor xmin="780" ymin="139" />
		<coor xmax="843" ymax="193" />
	</Char></CharAnno>
	<CharAnno><Char id="172" label="&#6035;" lineid="1">
		<coor xmin="845" ymin="137" />
		<coor xmax="898" ymax="193" />
	</Char></CharAnno>
	<CharAnno><Char id="173" label="&#6020;" lineid="1">
		<coor xmin="894" ymin="138" />
		<coor xmax="953" ymax="191" />
	</Char></CharAnno>
	<CharAnno><Char id="175" label="&#6020;" lineid="1">
		<coor xmin="952" ymin="144" />
		<coor xmax="1013" ymax="190" />
	</Char></CharAnno>
	<CharAnno><Char id="177" label="&#6031;" lineid="1">
		<coor xmin="1006" ymin="139" />
		<coor xmax="1074" ymax="187" />
	</Char></CharAnno>
	<CharAnno><Char id="179" label="&#6031;" lineid="1">
		<coor xmin="1150" ymin="138" />
		<coor xmax="1220" ymax="188" />
	</Char></CharAnno>
	<CharAnno><Char id="182" label="&#6048;" lineid="2">
		<coor xmin="218" ymin="211" />
		<coor xmax="304" ymax="267" />
	</Char></CharAnno>
	<CharAnno><Char id="183" label="&#6031;" lineid="2">
		<coor xmin="306" ymin="220" />
		<coor xmax="366" ymax="264" />
	</Char></CharAnno>
	<CharAnno><Char id="186" label="&#6035;" lineid="2">
		<coor xmin="403" ymin="213" />
		<coor xmax="455" ymax="266" />
	</Char></CharAnno>
	<CharAnno><Char id="190" label="&#6043;" lineid="2">
		<coor xmin="549" ymin="218" />
		<coor xmax="633" ymax="269" />
	</Char></CharAnno>
	<CharAnno><Char id="192" label="&#6016;" lineid="2">
		<coor xmin="661" ymin="218" />
		<coor xmax="727" ymax="267" />
	</Char></CharAnno>
	<CharAnno><Char id="194" label="&#6048;" lineid="2">
		<coor xmin="760" ymin="213" />
		<coor xmax="853" ymax="270" />
	</Char></CharAnno>
	<CharAnno><Char id="198" label="&#6017;" lineid="2">
		<coor xmin="926" ymin="213" />
		<coor xmax="982" ymax="262" />
	</Char></CharAnno>
	<CharAnno><Char id="200" label="&#6021;" lineid="2">
		<coor xmin="1062" ymin="214" />
		<coor xmax="1136" ymax="267" />
	</Char></CharAnno>
	<CharAnno><Char id="205" label="&#6033;" lineid="4">
		<coor xmin="52" ymin="371" />
		<coor xmax="107" ymax="424" />
	</Char></CharAnno>
	<CharAnno><Char id="207" label="&#6031;" lineid="4">
		<coor xmin="130" ymin="370" />
		<coor xmax="194" ymax="417" />
	</Char></CharAnno>
	<CharAnno><Char id="210" label="&#6031;" lineid="4">
		<coor xmin="305" ymin="378" />
		<coor xmax="376" ymax="424" />
	</Char></CharAnno>
	<CharAnno><Char id="212" label="&#6042;" lineid="4">
		<coor xmin="376" ymin="385" />
		<coor xmax="407" ymax="427" />
	</Char></CharAnno>
	<CharAnno><Char id="213" label="&#6016;" lineid="4">
		<coor xmin="408" ymin="381" />
		<coor xmax="475" ymax="429" />
	</Char></CharAnno>
	<CharAnno><Char id="215" label="&#6042;" lineid="4">
		<coor xmin="504" ymin="382" />
		<coor xmax="542" ymax="426" />
	</Char></CharAnno>
	<CharAnno><Char id="217" label="&#6033;" lineid="4">
		<coor xmin="572" ymin="372" />
		<coor xmax="635" ymax="429" />
	</Char></CharAnno>
	<CharAnno><Char id="220" label="&#6036;" lineid="4">
		<coor xmin="634" ymin="374" />
		<coor xmax="705" ymax="426" />
	</Char></CharAnno>
	<CharAnno><Char id="222" label="&#6031;" lineid="4">
		<coor xmin="807" ymin="368" />
		<coor xmax="875" ymax="418" />
	</Char></CharAnno>
	<CharAnno><Char id="223" label="&#6020;" lineid="4">
		<coor xmin="878" ymin="373" />
		<coor xmax="933" ymax="426" />
	</Char></CharAnno>
	<CharAnno><Char id="226" label="&#6050;" lineid="4">
		<coor xmin="934" ymin="370" />
		<coor xmax="1008" ymax="428" />
	</Char></CharAnno>
	<CharAnno><Char id="227" label="&#6040;" lineid="4">
		<coor xmin="1017" ymin="371" />
		<coor xmax="1076" ymax="425" />
	</Char></CharAnno>
	<CharAnno><Char id="229" label="&#6042;" lineid="4">
		<coor xmin="1079" ymin="369" />
		<coor xmax="1110" ymax="418" />
	</Char></CharAnno>
	<CharAnno><Char id="231" label="&#6041;" lineid="3">
		<coor xmin="202" ymin="298" />
		<coor xmax="298" ymax="348" />
	</Char></CharAnno>
	<CharAnno><Char id="233" label="&#6020;" lineid="3">
		<coor xmin="296" ymin="293" />
		<coor xmax="352" ymax="346" />
	</Char></CharAnno>
	<CharAnno><Char id="235" label="&#6035;" lineid="3">
		<coor xmin="387" ymin="290" />
		<coor xmax="446" ymax="356" />
	</Char></CharAnno>
	<CharAnno><Char id="238" label="&#6048;" lineid="3">
		<coor xmin="508" ymin="295" />
		<coor xmax="601" ymax="347" />
	</Char></CharAnno>
	<CharAnno><Char id="240" label="&#6020;" lineid="3">
		<coor xmin="648" ymin="288" />
		<coor xmax="711" ymax="342" />
	</Char></CharAnno>
	<CharAnno><Char id="241" label="&#6050;" lineid="3">
		<coor xmin="846" ymin="299" />
		<coor xmax="912" ymax="343" />
	</Char></CharAnno>
	<CharAnno><Char id="242" label="&#6047;" lineid="3">
		<coor xmin="920" ymin="297" />
		<coor xmax="1001" ymax="346" />
	</Char></CharAnno>
	<CharAnno><Char id="244" label="&#6020;" lineid="3">
		<coor xmin="997" ymin="289" />
		<coor xmax="1060" ymax="345" />
	</Char></CharAnno>
	<CharAnno><Char id="246" label="&#6031;" lineid="3">
		<coor xmin="1055" ymin="289" />
		<coor xmax="1130" ymax="342" />
	</Char></CharAnno>
	<CharAnno><Char id="249" label="&#6043;" lineid="0">
		<coor xmin="1113" ymin="62" />
		<coor xmax="1190" ymax="105" />
	</Char></CharAnno>
	<CharAnno><Char id="251" label="&#6016;" lineid="0">
		<coor xmin="1218" ymin="60" />
		<coor xmax="1281" ymax="114" />
	</Char></CharAnno>
	<CharAnno><Char id="253" label="&#6038;" lineid="0">
		<coor xmin="1307" ymin="58" />
		<coor xmax="1375" ymax="102" />
	</Char></CharAnno>
	<CharAnno><Char id="255" label="&#6043;" lineid="0">
		<coor xmin="1412" ymin="63" />
		<coor xmax="1511" ymax="117" />
	</Char></CharAnno>
	<CharAnno><Char id="257" label="&#6048;" lineid="0">
		<coor xmin="1544" ymin="60" />
		<coor xmax="1633" ymax="114" />
	</Char></CharAnno>
	<CharAnno><Char id="260" label="&#6038;" lineid="0">
		<coor xmin="1707" ymin="57" />
		<coor xmax="1778" ymax="113" />
	</Char></CharAnno>
	<CharAnno><Char id="270" label="&#6035;" lineid="1">
		<coor xmin="1292" ymin="133" />
		<coor xmax="1345" ymax="184" />
	</Char></CharAnno>
	<CharAnno><Char id="273" label="&#6021;" lineid="1">
		<coor xmin="1349" ymin="134" />
		<coor xmax="1414" ymax="187" />
	</Char></CharAnno>
	<CharAnno><Char id="274" label="&#6040;" lineid="1">
		<coor xmin="1411" ymin="131" />
		<coor xmax="1477" ymax="180" />
	</Char></CharAnno>
	<CharAnno><Char id="276" label="&#6020;" lineid="1">
		<coor xmin="1477" ymin="131" />
		<coor xmax="1537" ymax="184" />
	</Char></CharAnno>
	<CharAnno><Char id="278" label="&#6026;" lineid="1">
		<coor xmin="1718" ymin="133" />
		<coor xmax="1775" ymax="183" />
	</Char></CharAnno>
	<CharAnno><Char id="281" label="&#6048;" lineid="2">
		<coor xmin="1164" ymin="207" />
		<coor xmax="1265" ymax="263" />
	</Char></CharAnno>
	<CharAnno><Char id="283" label="&#6020;" lineid="2">
		<coor xmin="1311" ymin="206" />
		<coor xmax="1378" ymax="259" />
	</Char></CharAnno>
	<CharAnno><Char id="286" label="&#6031;" lineid="3">
		<coor xmin="1241" ymin="287" />
		<coor xmax="1306" ymax="338" />
	</Char></CharAnno>
	<CharAnno><Char id="288" label="&#6042;" lineid="3">
		<coor xmin="1307" ymin="288" />
		<coor xmax="1337" ymax="344" />
	</Char></CharAnno>
	<CharAnno><Char id="289" label="&#6016;" lineid="3">
		<coor xmin="1344" ymin="293" />
		<coor xmax="1408" ymax="345" />
	</Char></CharAnno>
	<CharAnno><Char id="291" label="&#6018;" lineid="4">
		<coor xmin="1142" ymin="368" />
		<coor xmax="1214" ymax="422" />
	</Char></CharAnno>
	<CharAnno><Char id="293" label="&#6041;" lineid="4">
		<coor xmin="1193" ymin="346" />
		<coor xmax="1236" ymax="374" />
	</Char></CharAnno>
	<CharAnno><Char id="296" label="&#6033;" lineid="4">
		<coor xmin="1241" ymin="373" />
		<coor xmax="1296" ymax="416" />
	</Char></CharAnno>
	<CharAnno><Char id="299" label="&#6036;" lineid="4">
		<coor xmin="1304" ymin="376" />
		<coor xmax="1373" ymax="426" />
	</Char></CharAnno>
	<CharAnno><Char id="301" label="&#6042;" lineid="3">
		<coor xmin="1447" ymin="287" />
		<coor xmax="1482" ymax="340" />
	</Char></CharAnno>
	<CharAnno><Char id="303" label="&#6033;" lineid="3">
		<coor xmin="1512" ymin="286" />
		<coor xmax="1575" ymax="341" />
	</Char></CharAnno>
	<CharAnno><Char id="306" label="&#6036;" lineid="3">
		<coor xmin="1578" ymin="292" />
		<coor xmax="1641" ymax="343" />
	</Char></CharAnno>
	<CharAnno><Char id="307" label="&#6042;" lineid="2">
		<coor xmin="1575" ymin="205" />
		<coor xmax="1605" ymax="255" />
	</Char></CharAnno>
	<CharAnno><Char id="309" label="&#6042;" lineid="2">
		<coor xmin="1613" ymin="216" />
		<coor xmax="1646" ymax="260" />
	</Char></CharAnno>
	<CharAnno><Char id="313" label="&#6038;" lineid="2">
		<coor xmin="1742" ymin="209" />
		<coor xmax="1804" ymax="251" />
	</Char></CharAnno>
	<CharAnno><Char id="316" label="&#6050;" lineid="4">
		<coor xmin="1497" ymin="371" />
		<coor xmax="1562" ymax="417" />
	</Char></CharAnno>
	<CharAnno><Char id="317" label="&#6047;" lineid="4">
		<coor xmin="1574" ymin="368" />
		<coor xmax="1655" ymax="419" />
	</Char></CharAnno>
	<CharAnno><Char id="319" label="&#6020;" lineid="4">
		<coor xmin="1648" ymin="361" />
		<coor xmax="1708" ymax="417" />
	</Char></CharAnno>
	<CharAnno><Char id="320" label="&#6031;" lineid="4">
		<coor xmin="1703" ymin="361" />
		<coor xmax="1772" ymax="412" />
	</Char></CharAnno>
	<CharAnno><Char id="324" label="&#6023;" lineid="4">
		<coor xmin="1832" ymin="361" />
		<coor xmax="1897" ymax="416" />
	</Char></CharAnno>
</Annotation>