<Annotation>
	<CharAnno><Char id="1" label="&#6035;" lineid="0">
		<coor xmin="560" ymin="62" />
		<coor xmax="613" ymax="110" />
	</Char></CharAnno>
	<CharAnno><Char id="3" label="&#6040;" lineid="0">
		<coor xmin="771" ymin="64" />
		<coor xmax="828" ymax="103" />
	</Char></CharAnno>
	<CharAnno><Char id="5" label="&#6035;" lineid="0">
		<coor xmin="826" ymin="61" />
		<coor xmax="874" ymax="105" />
	</Char></CharAnno>
	<CharAnno><Char id="7" label="&#6048;" lineid="0">
		<coor xmin="898" ymin="61" />
		<coor xmax="969" ymax="106" />
	</Char></CharAnno>
	<CharAnno><Char id="10" label="&#6040;" lineid="0">
		<coor xmin="1070" ymin="58" />
		<coor xmax="1129" ymax="107" />
	</Char></CharAnno>
	<CharAnno><Char id="12" label="&#6043;" lineid="0">
		<coor xmin="1176" ymin="56" />
		<coor xmax="1249" ymax="106" />
	</Char></CharAnno>
	<CharAnno><Char id="14" label="&#6050;" lineid="0">
		<coor xmin="1299" ymin="59" />
		<coor xmax="1365" ymax="103" />
	</Char></CharAnno>
	<CharAnno><Char id="16" label="&#6016;" lineid="0">
		<coor xmin="1365" ymin="63" />
		<coor xmax="1425" ymax="103" />
	</Char></CharAnno>
	<CharAnno><Char id="21" label="&#6041;" lineid="0">
		<coor xmin="1541" ymin="55" />
		<coor xmax="1616" ymax="109" />
	</Char></CharAnno>
	<CharAnno><Char id="77" label="&#6043;" lineid="1">
		<coor xmin="573" ymin="135" />
		<coor xmax="638" ymax="175" />
	</Char></CharAnno>
	<CharAnno><Char id="79" label="&#6039;" lineid="1">
		<coor xmin="666" ymin="127" />
		<coor xmax="726" ymax="178" />
	</Char></CharAnno>
	<CharAnno><Char id="82" label="&#6033;" lineid="1">
		<coor xmin="819" ymin="130" />
		<coor xmax="871" ymax="175" />
	</Char></CharAnno>
	<CharAnno><Char id="84" label="&#6047;" lineid="1">
		<coor xmin="899" ymin="125" />
		<coor xmax="974" ymax="181" />
	</Char></CharAnno>
	<CharAnno><Char id="86" label="&#6050;" lineid="1">
		<coor xmin="980" ymin="131" />
		<coor xmax="1034" ymax="175" />
	</Char></CharAnno>
	<CharAnno><Char id="88" label="&#6021;" lineid="1">
		<coor xmin="1066" ymin="130" />
		<coor xmax="1119" ymax="179" />
	</Char></CharAnno>
	<CharAnno><Char id="89" label="&#6036;" lineid="1">
		<coor xmin="1120" ymin="134" />
		<coor xmax="1179" ymax="181" />
	</Char></CharAnno>
	<CharAnno><Char id="90" label="&#6020;" lineid="1">
		<coor xmin="1178" ymin="130" />
		<coor xmax="1229" ymax="179" />
	</Char></CharAnno>
	<CharAnno><Char id="92" label="&#6035;" lineid="1">
		<coor xmin="1228" ymin="130" />
		<coor xmax="1281" ymax="179" />
	</Char></CharAnno>
	<CharAnno><Char id="94" label="&#6044;" lineid="1">
		<coor xmin="1279" ymin="128" />
		<coor xmax="1329" ymax="174" />
	</Char></CharAnno>
	<CharAnno><Char id="96" label="&#6043;" lineid="1">
		<coor xmin="1358" ymin="131" />
		<coor xmax="1429" ymax="176" />
	</Char></CharAnno>
	<CharAnno><Char id="98" label="&#6039;" lineid="1">
		<coor xmin="1459" ymin="129" />
		<coor xmax="1526" ymax="176" />
	</Char></CharAnno>
	<CharAnno><Char id="153" label="&#6048;" lineid="2">
		<coor xmin="639" ymin="203" />
		<coor xmax="719" ymax="253" />
	</Char></CharAnno>
	<CharAnno><Char id="155" label="&#6021;" lineid="2">
		<coor xmin="743" ymin="208" />
		<coor xmax="789" ymax="253" />
	</Char></CharAnno>
	<CharAnno><Char id="157" label="&#6042;" lineid="2">
		<coor xmin="818" ymin="209" />
		<coor xmax="852" ymax="250" />
	</Char></CharAnno>
	<CharAnno><Char id="159" label="&#6023;" lineid="2">
		<coor xmin="869" ymin="201" />
		<coor xmax="923" ymax="254" />
	</Char></CharAnno>
	<CharAnno><Char id="160" label="&#6036;" lineid="2">
		<coor xmin="919" ymin="206" />
		<coor xmax="979" ymax="255" />
	</Char></CharAnno>
	<CharAnno><Char id="162" label="&#6031;" lineid="2">
		<coor xmin="1072" ymin="199" />
		<coor xmax="1135" ymax="250" />
	</Char></CharAnno>
	<CharAnno><Char id="165" label="&#6021;" lineid="2">
		<coor xmin="1373" ymin="201" />
		<coor xmax="1422" ymax="250" />
	</Char></CharAnno>
	<CharAnno><Char id="168" label="&#6047;" lineid="2">
		<coor xmin="1461" ymin="199" />
		<coor xmax="1531" ymax="245" />
	</Char></CharAnno>
	<CharAnno><Char id="224" label="&#6040;" lineid="3">
		<coor xmin="572" ymin="272" />
		<coor xmax="635" ymax="322" />
	</Char></CharAnno>
	<CharAnno><Char id="226" label="&#6021;" lineid="3">
		<coor xmin="632" ymin="268" />
		<coor xmax="689" ymax="317" />
	</Char></CharAnno>
	<CharAnno><Char id="231" label="&#6041;" lineid="3">
		<coor xmin="870" ymin="268" />
		<coor xmax="945" ymax="320" />
	</Char></CharAnno>
	<CharAnno><Char id="232" label="&#6050;" lineid="3">
		<coor xmin="941" ymin="268" />
		<coor xmax="1008" ymax="318" />
	</Char></CharAnno>
	<CharAnno><Char id="236" label="&#6040;" lineid="3">
		<coor xmin="1098" ymin="272" />
		<coor xmax="1159" ymax="316" />
	</Char></CharAnno>
	<CharAnno><Char id="237" label="&#6016;" lineid="3">
		<coor xmin="1155" ymin="267" />
		<coor xmax="1215" ymax="314" />
	</Char></CharAnno>
	<CharAnno><Char id="238" label="&#6040;" lineid="3">
		<coor xmin="1207" ymin="270" />
		<coor xmax="1268" ymax="315" />
	</Char></CharAnno>
	<CharAnno><Char id="240" label="&#6035;" lineid="3">
		<coor xmin="1293" ymin="267" />
		<coor xmax="1346" ymax="320" />
	</Char></CharAnno>
	<CharAnno><Char id="241" label="&#6021;" lineid="3">
		<coor xmin="1345" ymin="268" />
		<coor xmax="1403" ymax="322" />
	</Char></CharAnno>
	<CharAnno><Char id="243" label="&#6031;" lineid="3">
		<coor xmin="1402" ymin="267" />
		<coor xmax="1460" ymax="316" />
	</Char></CharAnno>
	<CharAnno><Char id="299" label="&#6043;" lineid="4">
		<coor xmin="576" ymin="351" />
		<coor xmax="644" ymax="397" />
	</Char></CharAnno>
	<CharAnno><Char id="301" label="&#6039;" lineid="4">
		<coor xmin="674" ymin="351" />
		<coor xmax="732" ymax="396" />
	</Char></CharAnno>
	<CharAnno><Char id="303" label="&#6035;" lineid="4">
		<coor xmin="761" ymin="350" />
		<coor xmax="805" ymax="401" />
	</Char></CharAnno>
	<CharAnno><Char id="307" label="&#6043;" lineid="4">
		<coor xmin="941" ymin="351" />
		<coor xmax="1016" ymax="398" />
	</Char></CharAnno>
	<CharAnno><Char id="308" label="&#6036;" lineid="4">
		<coor xmin="1014" ymin="352" />
		<coor xmax="1077" ymax="397" />
	</Char></CharAnno>
	<CharAnno><Char id="309" label="&#6042;" lineid="4">
		<coor xmin="1077" ymin="351" />
		<coor xmax="1107" ymax="396" />
	</Char></CharAnno>
	<CharAnno><Char id="311" label="&#6047;" lineid="4">
		<coor xmin="1111" ymin="345" />
		<coor xmax="1191" ymax="396" />
	</Char></CharAnno>
	<CharAnno><Char id="316" label="&#6048;" lineid="4">
		<coor xmin="1282" ymin="347" />
		<coor xmax="1370" ymax="398" />
	</Char></CharAnno>
	<CharAnno><Char id="318" label="&#6020;" lineid="4">
		<coor xmin="1410" ymin="348" />
		<coor xmax="1467" ymax="398" />
	</Char></CharAnno>
	<CharAnno><Char id="400" label="&#6033;" lineid="4">
		<coor xmin="1186" ymin="351" />
		<coor xmax="1251" ymax="398" />
	</Char></CharAnno>
	<CharAnno><Char id="404" label="&#6035;" lineid="0">
		<coor xmin="1123" ymin="63" />
		<coor xmax="1180" ymax="108" />
	</Char></CharAnno>
	<CharAnno><Char id="428" label="&#6030;" lineid="2">
		<coor xmin="979" ymin="204" />
		<coor xmax="1074" ymax="256" />
	</Char></CharAnno>
	<CharAnno><Char id="431" label="&#6043;" lineid="3">
		<coor xmin="712" ymin="269" />
		<coor xmax="793" ymax="318" />
	</Char></CharAnno>
</Annotation>