<Annotation>
	<CharAnno><Char id="314" label="&#6043;" lineid="4">
		<coor xmin="19" ymin="374" />
		<coor xmax="94" ymax="421" />
	</Char></CharAnno>
	<CharAnno><Char id="316" label="&#6020;" lineid="0">
		<coor xmin="65" ymin="54" />
		<coor xmax="139" ymax="113" />
	</Char></CharAnno>
	<CharAnno><Char id="317" label="&#6043;" lineid="0">
		<coor xmin="158" ymin="52" />
		<coor xmax="219" ymax="104" />
	</Char></CharAnno>
	<CharAnno><Char id="321" label="&#6044;" lineid="2">
		<coor xmin="205" ymin="202" />
		<coor xmax="249" ymax="261" />
	</Char></CharAnno>
	<CharAnno><Char id="322" label="&#6031;" lineid="2">
		<coor xmin="251" ymin="210" />
		<coor xmax="314" ymax="267" />
	</Char></CharAnno>
	<CharAnno><Char id="323" label="&#6050;" lineid="3">
		<coor xmin="209" ymin="290" />
		<coor xmax="266" ymax="341" />
	</Char></CharAnno>
	<CharAnno><Char id="324" label="&#6020;" lineid="3">
		<coor xmin="262" ymin="283" />
		<coor xmax="327" ymax="339" />
	</Char></CharAnno>
	<CharAnno><Char id="326" label="&#6048;" lineid="4">
		<coor xmin="231" ymin="373" />
		<coor xmax="305" ymax="425" />
	</Char></CharAnno>
	<CharAnno><Char id="328" label="&#6016;" lineid="4">
		<coor xmin="337" ymin="375" />
		<coor xmax="402" ymax="425" />
	</Char></CharAnno>
	<CharAnno><Char id="330" label="&#6035;" lineid="1">
		<coor xmin="328" ymin="132" />
		<coor xmax="388" ymax="177" />
	</Char></CharAnno>
	<CharAnno><Char id="332" label="&#6035;" lineid="1">
		<coor xmin="389" ymin="128" />
		<coor xmax="457" ymax="195" />
	</Char></CharAnno>
	<CharAnno><Char id="335" label="&#6031;" lineid="0">
		<coor xmin="381" ymin="55" />
		<coor xmax="438" ymax="114" />
	</Char></CharAnno>
	<CharAnno><Char id="336" label="&#6035;" lineid="1">
		<coor xmin="451" ymin="131" />
		<coor xmax="499" ymax="186" />
	</Char></CharAnno>
	<CharAnno><Char id="338" label="&#6020;" lineid="1">
		<coor xmin="523" ymin="128" />
		<coor xmax="588" ymax="187" />
	</Char></CharAnno>
	<CharAnno><Char id="339" label="&#6021;" lineid="2">
		<coor xmin="430" ymin="216" />
		<coor xmax="484" ymax="261" />
	</Char></CharAnno>
	<CharAnno><Char id="341" label="&#6042;" lineid="2">
		<coor xmin="483" ymin="216" />
		<coor xmax="510" ymax="263" />
	</Char></CharAnno>
	<CharAnno><Char id="342" label="&#6038;" lineid="3">
		<coor xmin="329" ymin="290" />
		<coor xmax="387" ymax="341" />
	</Char></CharAnno>
	<CharAnno><Char id="343" label="&#6020;" lineid="3">
		<coor xmin="384" ymin="287" />
		<coor xmax="447" ymax="340" />
	</Char></CharAnno>
	<CharAnno><Char id="347" label="&#6038;" lineid="4">
		<coor xmin="496" ymin="373" />
		<coor xmax="552" ymax="419" />
	</Char></CharAnno>
	<CharAnno><Char id="350" label="&#6023;" lineid="0">
		<coor xmin="461" ymin="50" />
		<coor xmax="528" ymax="114" />
	</Char></CharAnno>
	<CharAnno><Char id="353" label="&#6020;" lineid="0">
		<coor xmin="542" ymin="27" />
		<coor xmax="624" ymax="107" />
	</Char></CharAnno>
	<CharAnno><Char id="356" label="&#6038;" lineid="3">
		<coor xmin="481" ymin="292" />
		<coor xmax="541" ymax="333" />
	</Char></CharAnno>
	<CharAnno><Char id="358" label="&#6033;" lineid="3">
		<coor xmin="546" ymin="289" />
		<coor xmax="596" ymax="339" />
	</Char></CharAnno>
	<CharAnno><Char id="361" label="&#6042;" lineid="3">
		<coor xmin="619" ymin="289" />
		<coor xmax="660" ymax="342" />
	</Char></CharAnno>
	<CharAnno><Char id="362" label="&#6047;" lineid="4">
		<coor xmin="561" ymin="369" />
		<coor xmax="620" ymax="418" />
	</Char></CharAnno>
	<CharAnno><Char id="365" label="&#6042;" lineid="1">
		<coor xmin="577" ymin="122" />
		<coor xmax="618" ymax="185" />
	</Char></CharAnno>
	<CharAnno><Char id="367" label="&#6018;" lineid="1">
		<coor xmin="644" ymin="132" />
		<coor xmax="704" ymax="183" />
	</Char></CharAnno>
	<CharAnno><Char id="369" label="&#6023;" lineid="0">
		<coor xmin="608" ymin="53" />
		<coor xmax="673" ymax="109" />
	</Char></CharAnno>
	<CharAnno><Char id="371" label="&#6016;" lineid="0">
		<coor xmin="675" ymin="52" />
		<coor xmax="740" ymax="106" />
	</Char></CharAnno>
	<CharAnno><Char id="372" label="&#6031;" lineid="2">
		<coor xmin="576" ymin="202" />
		<coor xmax="632" ymax="265" />
	</Char></CharAnno>
	<CharAnno><Char id="373" label="&#6035;" lineid="2">
		<coor xmin="663" ymin="213" />
		<coor xmax="710" ymax="263" />
	</Char></CharAnno>
	<CharAnno><Char id="376" label="&#6035;" lineid="2">
		<coor xmin="752" ymin="210" />
		<coor xmax="801" ymax="262" />
	</Char></CharAnno>
	<CharAnno><Char id="379" label="&#6042;" lineid="3">
		<coor xmin="759" ymin="291" />
		<coor xmax="796" ymax="338" />
	</Char></CharAnno>
	<CharAnno><Char id="381" label="&#6018;" lineid="3">
		<coor xmin="822" ymin="290" />
		<coor xmax="873" ymax="342" />
	</Char></CharAnno>
	<CharAnno><Char id="383" label="&#6040;" lineid="3">
		<coor xmin="900" ymin="290" />
		<coor xmax="956" ymax="338" />
	</Char></CharAnno>
	<CharAnno><Char id="385" label="&#6043;" lineid="4">
		<coor xmin="646" ymin="375" />
		<coor xmax="726" ymax="420" />
	</Char></CharAnno>
	<CharAnno><Char id="387" label="&#6036;" lineid="4">
		<coor xmin="719" ymin="369" />
		<coor xmax="779" ymax="418" />
	</Char></CharAnno>
	<CharAnno><Char id="389" label="&#6035;" lineid="4">
		<coor xmin="783" ymin="366" />
		<coor xmax="851" ymax="433" />
	</Char></CharAnno>
	<CharAnno><Char id="391" label="&#6016;" lineid="1">
		<coor xmin="764" ymin="130" />
		<coor xmax="824" ymax="195" />
	</Char></CharAnno>
	<CharAnno><Char id="392" label="&#6044;" lineid="1">
		<coor xmin="815" ymin="131" />
		<coor xmax="879" ymax="188" />
	</Char></CharAnno>
	<CharAnno><Char id="395" label="&#6016;" lineid="1">
		<coor xmin="874" ymin="131" />
		<coor xmax="937" ymax="191" />
	</Char></CharAnno>
	<CharAnno><Char id="396" label="&#6038;" lineid="4">
		<coor xmin="852" ymin="371" />
		<coor xmax="921" ymax="416" />
	</Char></CharAnno>
	<CharAnno><Char id="400" label="&#6042;" lineid="4">
		<coor xmin="1001" ymin="361" />
		<coor xmax="1033" ymax="421" />
	</Char></CharAnno>
	<CharAnno><Char id="401" label="&#6036;" lineid="4">
		<coor xmin="1162" ymin="369" />
		<coor xmax="1223" ymax="417" />
	</Char></CharAnno>
	<CharAnno><Char id="404" label="&#6035;" lineid="4">
		<coor xmin="1222" ymin="365" />
		<coor xmax="1293" ymax="426" />
	</Char></CharAnno>
	<CharAnno><Char id="405" label="&#6041;" lineid="3">
		<coor xmin="980" ymin="285" />
		<coor xmax="1065" ymax="342" />
	</Char></CharAnno>
	<CharAnno><Char id="407" label="&#6042;" lineid="3">
		<coor xmin="1082" ymin="285" />
		<coor xmax="1120" ymax="343" />
	</Char></CharAnno>
	<CharAnno><Char id="408" label="&#6026;" lineid="3">
		<coor xmin="1143" ymin="271" />
		<coor xmax="1197" ymax="340" />
	</Char></CharAnno>
	<CharAnno><Char id="411" label="&#6041;" lineid="3">
		<coor xmin="1210" ymin="289" />
		<coor xmax="1291" ymax="341" />
	</Char></CharAnno>
	<CharAnno><Char id="412" label="&#6020;" lineid="2">
		<coor xmin="1256" ymin="190" />
		<coor xmax="1330" ymax="265" />
	</Char></CharAnno>
	<CharAnno><Char id="413" label="&#6036;" lineid="2">
		<coor xmin="1194" ymin="212" />
		<coor xmax="1255" ymax="259" />
	</Char></CharAnno>
	<CharAnno><Char id="414" label="&#6033;" lineid="1">
		<coor xmin="1251" ymin="134" />
		<coor xmax="1300" ymax="191" />
	</Char></CharAnno>
	<CharAnno><Char id="416" label="&#6042;" lineid="0">
		<coor xmin="1268" ymin="51" />
		<coor xmax="1298" ymax="98" />
	</Char></CharAnno>
	<CharAnno><Char id="417" label="&#6031;" lineid="0">
		<coor xmin="1219" ymin="50" />
		<coor xmax="1274" ymax="99" />
	</Char></CharAnno>
	<CharAnno><Char id="420" label="&#6035;" lineid="0">
		<coor xmin="1137" ymin="45" />
		<coor xmax="1200" ymax="108" />
	</Char></CharAnno>
	<CharAnno><Char id="421" label="&#6040;" lineid="0">
		<coor xmin="1066" ymin="51" />
		<coor xmax="1117" ymax="105" />
	</Char></CharAnno>
	<CharAnno><Char id="424" label="&#6036;" lineid="0">
		<coor xmin="900" ymin="58" />
		<coor xmax="949" ymax="95" />
	</Char></CharAnno>
	<CharAnno><Char id="426" label="&#6043;" lineid="1">
		<coor xmin="936" ymin="134" />
		<coor xmax="1010" ymax="183" />
	</Char></CharAnno>
	<CharAnno><Char id="427" label="&#6021;" lineid="2">
		<coor xmin="822" ymin="216" />
		<coor xmax="871" ymax="266" />
	</Char></CharAnno>
	<CharAnno><Char id="430" label="&#6036;" lineid="2">
		<coor xmin="895" ymin="213" />
		<coor xmax="958" ymax="264" />
	</Char></CharAnno>
	<CharAnno><Char id="431" label="&#6030;" lineid="1">
		<coor xmin="1059" ymin="137" />
		<coor xmax="1145" ymax="198" />
	</Char></CharAnno>
	<CharAnno><Char id="432" label="&#6021;" lineid="0">
		<coor xmin="983" ymin="53" />
		<coor xmax="1036" ymax="94" />
	</Char></CharAnno>
	<CharAnno><Char id="439" label="&#6020;" lineid="2">
		<coor xmin="957" ymin="205" />
		<coor xmax="1025" ymax="270" />
	</Char></CharAnno>
	<CharAnno><Char id="440" label="&#6042;" lineid="2">
		<coor xmin="1017" ymin="216" />
		<coor xmax="1054" ymax="259" />
	</Char></CharAnno>
</Annotation>