<Annotation>
	<SubSylAnno><SubSyl id="145" label="&#6017;&#6098;&#6047;&#6081;" lineid="0">
		<coor xmin="60" ymin="20" />
		<coor xmax="190" ymax="110" />
	</SubSyl></SubSylAnno>
	<SubSylAnno><SubSyl id="148" label="&#6032;&#6070;&#6098;&#6043;" lineid="4">
		<coor xmin="24" ymin="310" />
		<coor xmax="124" ymax="437" />
	</SubSyl></SubSylAnno>
	<SubSylAnno><SubSyl id="149" label="&#6016;&#6098;&#6035;&#6075;" lineid="4">
		<coor xmin="121" ymin="340" />
		<coor xmax="190" ymax="436" />
	</SubSyl></SubSylAnno>
	<SubSylAnno><SubSyl id="150" label="&#6020;" lineid="4">
		<coor xmin="189" ymin="342" />
		<coor xmax="250" ymax="403" />
	</SubSyl></SubSylAnno>
	<SubSylAnno><SubSyl id="151" label="&#6047;&#6098;&#6042;&#6087;" lineid="4">
		<coor xmin="249" ymin="323" />
		<coor xmax="367" ymax="416" />
	</SubSyl></SubSylAnno>
	<SubSylAnno><SubSyl id="152" label="&#6037;" lineid="4">
		<coor xmin="368" ymin="329" />
		<coor xmax="431" ymax="404" />
	</SubSyl></SubSylAnno>
	<SubSylAnno><SubSyl id="153" label="&#6020;" lineid="4">
		<coor xmin="429" ymin="351" />
		<coor xmax="492" ymax="406" />
	</SubSyl></SubSylAnno>
	<SubSylAnno><SubSyl id="154" label="&#6021;" lineid="0">
		<coor xmin="168" ymin="18" />
		<coor xmax="237" ymax="91" />
	</SubSyl></SubSylAnno>
	<SubSylAnno><SubSyl id="155" label="&#6016;&#6086;" lineid="0">
		<coor xmin="236" ymin="16" />
		<coor xmax="302" ymax="98" />
	</SubSyl></SubSylAnno>
	<SubSylAnno><SubSyl id="156" label="&#6036;&#6075;" lineid="0">
		<coor xmin="303" ymin="37" />
		<coor xmax="361" ymax="110" />
	</SubSyl></SubSylAnno>
	<SubSylAnno><SubSyl id="157" label="&#6031;" lineid="0">
		<coor xmin="362" ymin="22" />
		<coor xmax="434" ymax="84" />
	</SubSyl></SubSylAnno>
	<SubSylAnno><SubSyl id="158" label="&#6037;&#6098;&#6033;&#6083;" lineid="1">
		<coor xmin="265" ymin="93" />
		<coor xmax="367" ymax="195" />
	</SubSyl></SubSylAnno>
	<SubSylAnno><SubSyl id="159" label="&#6016;&#6098;&#6042;&#6084;" lineid="1">
		<coor xmin="366" ymin="86" />
		<coor xmax="494" ymax="181" />
	</SubSyl></SubSylAnno>
	<SubSylAnno><SubSyl id="160" label="&#6031;" lineid="2">
		<coor xmin="145" ymin="175" />
		<coor xmax="224" ymax="236" />
	</SubSyl></SubSylAnno>
	<SubSylAnno><SubSyl id="161" label="&#6023;&#6098;&#6023;&#6081;" lineid="2">
		<coor xmin="219" ymin="171" />
		<coor xmax="314" ymax="267" />
	</SubSyl></SubSylAnno>
	<SubSylAnno><SubSyl id="163" label="&#6033;&#6098;&#6042;" lineid="2">
		<coor xmin="366" ymin="172" />
		<coor xmax="443" ymax="258" />
	</SubSyl></SubSylAnno>
	<SubSylAnno><SubSyl id="164" label="&#6035;" lineid="2">
		<coor xmin="314" ymin="192" />
		<coor xmax="373" ymax="252" />
	</SubSyl></SubSylAnno>
	<SubSylAnno><SubSyl id="165" label="&#6020;&#6091;" lineid="2">
		<coor xmin="441" ymin="172" />
		<coor xmax="506" ymax="243" />
	</SubSyl></SubSylAnno>
	<SubSylAnno><SubSyl id="166" label="&#6047;&#6098;&#6042;" lineid="3">
		<coor xmin="142" ymin="244" />
		<coor xmax="241" ymax="330" />
	</SubSyl></SubSylAnno>
	<SubSylAnno><SubSyl id="167" label="&#6026;&#6072;" lineid="3">
		<coor xmin="241" ymin="254" />
		<coor xmax="303" ymax="325" />
	</SubSyl></SubSylAnno>
	<SubSylAnno><SubSyl id="168" label="&#6018;&#6077;" lineid="3">
		<coor xmin="421" ymin="270" />
		<coor xmax="488" ymax="345" />
	</SubSyl></SubSylAnno>
	<SubSylAnno><SubSyl id="169" label="&#6031;&#6098;&#6041;&#6076;" lineid="0">
		<coor xmin="437" ymin="36" />
		<coor xmax="534" ymax="124" />
	</SubSyl></SubSylAnno>
	<SubSylAnno><SubSyl id="170" label="&#6020;" lineid="0">
		<coor xmin="530" ymin="36" />
		<coor xmax="591" ymax="103" />
	</SubSyl></SubSylAnno>
	<SubSylAnno><SubSyl id="171" label="&#6040;" lineid="1">
		<coor xmin="489" ymin="123" />
		<coor xmax="546" ymax="175" />
	</SubSyl></SubSylAnno>
	<SubSylAnno><SubSyl id="172" label="&#6047;&#6073;" lineid="1">
		<coor xmin="553" ymin="107" />
		<coor xmax="629" ymax="176" />
	</SubSyl></SubSylAnno>
	<SubSylAnno><SubSyl id="173" label="&#6020;" lineid="1">
		<coor xmin="632" ymin="112" />
		<coor xmax="686" ymax="169" />
	</SubSyl></SubSylAnno>
	<SubSylAnno><SubSyl id="175" label="&#6044;&#6071;" lineid="1">
		<coor xmin="669" ymin="102" />
		<coor xmax="726" ymax="169" />
	</SubSyl></SubSylAnno>
	<SubSylAnno><SubSyl id="176" label="&#6035;&#6070;" lineid="1">
		<coor xmin="725" ymin="118" />
		<coor xmax="808" ymax="173" />
	</SubSyl></SubSylAnno>
	<SubSylAnno><SubSyl id="177" label="&#6047;" lineid="1">
		<coor xmin="807" ymin="116" />
		<coor xmax="887" ymax="177" />
	</SubSyl></SubSylAnno>
	<SubSylAnno><SubSyl id="178" label="&#6016;&#6098;&#6047;" lineid="0">
		<coor xmin="800" ymin="43" />
		<coor xmax="896" ymax="117" />
	</SubSyl></SubSylAnno>
	<SubSylAnno><SubSyl id="179" label="&#6031;&#6098;&#6042;" lineid="0">
		<coor xmin="884" ymin="11" />
		<coor xmax="965" ymax="105" />
	</SubSyl></SubSylAnno>
	<SubSylAnno><SubSyl id="180" label="&#6016;&#6098;&#6047;&#6070;" lineid="0">
		<coor xmin="966" ymin="45" />
		<coor xmax="1089" ymax="120" />
	</SubSyl></SubSylAnno>
	<SubSylAnno><SubSyl id="181" label="&#6035;&#6098;&#6031;" lineid="0">
		<coor xmin="1086" ymin="36" />
		<coor xmax="1158" ymax="126" />
	</SubSyl></SubSylAnno>
	<SubSylAnno><SubSyl id="182" label="&#6053;" lineid="0">
		<coor xmin="1144" ymin="35" />
		<coor xmax="1208" ymax="96" />
	</SubSyl></SubSylAnno>
	<SubSylAnno><SubSyl id="183" label="&#6031;" lineid="0">
		<coor xmin="1200" ymin="46" />
		<coor xmax="1263" ymax="99" />
	</SubSyl></SubSylAnno>
	<SubSylAnno><SubSyl id="184" label="&#6042;&#6072;" lineid="1">
		<coor xmin="1043" ymin="115" />
		<coor xmax="1082" ymax="173" />
	</SubSyl></SubSylAnno>
	<SubSylAnno><SubSyl id="185" label="&#6050;" lineid="1">
		<coor xmin="1083" ymin="129" />
		<coor xmax="1150" ymax="173" />
	</SubSyl></SubSylAnno>
	<SubSylAnno><SubSyl id="186" label="&#6047;&#6091;" lineid="1">
		<coor xmin="1152" ymin="109" />
		<coor xmax="1221" ymax="175" />
	</SubSyl></SubSylAnno>
	<SubSylAnno><SubSyl id="187" label="&#6023;&#6078;" lineid="2">
		<coor xmin="500" ymin="175" />
		<coor xmax="601" ymax="244" />
	</SubSyl></SubSylAnno>
	<SubSylAnno><SubSyl id="188" label="&#6020;" lineid="2">
		<coor xmin="598" ymin="185" />
		<coor xmax="657" ymax="242" />
	</SubSyl></SubSylAnno>
	<SubSylAnno><SubSyl id="189" label="&#6036;&#6077;" lineid="2">
		<coor xmin="663" ymin="193" />
		<coor xmax="739" ymax="264" />
	</SubSyl></SubSylAnno>
	<SubSylAnno><SubSyl id="190" label="&#6035;" lineid="2">
		<coor xmin="727" ymin="194" />
		<coor xmax="788" ymax="244" />
	</SubSyl></SubSylAnno>
	<SubSylAnno><SubSyl id="191" label="&#6026;&#6086;" lineid="2">
		<coor xmin="892" ymin="175" />
		<coor xmax="952" ymax="250" />
	</SubSyl></SubSylAnno>
	<SubSylAnno><SubSyl id="192" label="&#6030;&#6078;" lineid="2">
		<coor xmin="948" ymin="177" />
		<coor xmax="1081" ymax="252" />
	</SubSyl></SubSylAnno>
	<SubSylAnno><SubSyl id="193" label="&#6017;&#6098;&#6043;&#6077;" lineid="2">
		<coor xmin="1080" ymin="197" />
		<coor xmax="1147" ymax="281" />
	</SubSyl></SubSylAnno>
	<SubSylAnno><SubSyl id="194" label="&#6035;" lineid="2">
		<coor xmin="1138" ymin="188" />
		<coor xmax="1196" ymax="258" />
	</SubSyl></SubSylAnno>
	<SubSylAnno><SubSyl id="195" label="&#6036;&#6072;" lineid="2">
		<coor xmin="1193" ymin="180" />
		<coor xmax="1262" ymax="253" />
	</SubSyl></SubSylAnno>
	<SubSylAnno><SubSyl id="196" label="&#6036;&#6098;&#6042;" lineid="3">
		<coor xmin="484" ymin="245" />
		<coor xmax="560" ymax="338" />
	</SubSyl></SubSylAnno>
	<SubSylAnno><SubSyl id="197" label="&#6030;&#6072;" lineid="3">
		<coor xmin="558" ymin="258" />
		<coor xmax="671" ymax="323" />
	</SubSyl></SubSylAnno>
	<SubSylAnno><SubSyl id="198" label="&#6039;&#6072;" lineid="3">
		<coor xmin="672" ymin="265" />
		<coor xmax="731" ymax="325" />
	</SubSyl></SubSylAnno>
	<SubSylAnno><SubSyl id="199" label="&#6035;&#6083;" lineid="3">
		<coor xmin="725" ymin="254" />
		<coor xmax="823" ymax="328" />
	</SubSyl></SubSylAnno>
	<SubSylAnno><SubSyl id="200" label="&#6021;&#6083;" lineid="3">
		<coor xmin="804" ymin="254" />
		<coor xmax="926" ymax="327" />
	</SubSyl></SubSylAnno>
	<SubSylAnno><SubSyl id="201" label="&#6036;&#6098;&#6042;&#6078;" lineid="3">
		<coor xmin="1103" ymin="255" />
		<coor xmax="1197" ymax="331" />
	</SubSyl></SubSylAnno>
	<SubSylAnno><SubSyl id="202" label="&#6016;&#6075;&#6086;" lineid="4">
		<coor xmin="605" ymin="333" />
		<coor xmax="672" ymax="445" />
	</SubSyl></SubSylAnno>
	<SubSylAnno><SubSyl id="203" label="&#6065;&#6098;&#6041;" lineid="4">
		<coor xmin="676" ymin="331" />
		<coor xmax="753" ymax="414" />
	</SubSyl></SubSylAnno>
	<SubSylAnno><SubSyl id="204" label="&#6022;&#6098;&#6018;" lineid="4">
		<coor xmin="751" ymin="341" />
		<coor xmax="813" ymax="442" />
	</SubSyl></SubSylAnno>
	<SubSylAnno><SubSyl id="205" label="&#6020;" lineid="4">
		<coor xmin="800" ymin="348" />
		<coor xmax="856" ymax="407" />
	</SubSyl></SubSylAnno>
	<SubSylAnno><SubSyl id="206" label="&#6043;&#6098;&#6050;" lineid="4">
		<coor xmin="853" ymin="358" />
		<coor xmax="947" ymax="433" />
	</SubSyl></SubSylAnno>
	<SubSylAnno><SubSyl id="207" label="&#6016;&#6091;" lineid="4">
		<coor xmin="946" ymin="327" />
		<coor xmax="1009" ymax="405" />
	</SubSyl></SubSylAnno>
	<SubSylAnno><SubSyl id="208" label="&#6030;&#6070;" lineid="4">
		<coor xmin="1011" ymin="355" />
		<coor xmax="1153" ymax="407" />
	</SubSyl></SubSylAnno>
	<SubSylAnno><SubSyl id="209" label="&#6047;&#6084;" lineid="4">
		<coor xmin="1160" ymin="352" />
		<coor xmax="1288" ymax="416" />
	</SubSyl></SubSylAnno>
	<SubSylAnno><SubSyl id="210" label="&#6031;" lineid="4">
		<coor xmin="1282" ymin="342" />
		<coor xmax="1363" ymax="418" />
	</SubSyl></SubSylAnno>
</Annotation>